{
   "n_download_no_trigger" : 1,
   "start_activity" : "download_0",
   "name" : "modified.testbed.localhost_www.kidsfoni.com_",
   "load_activity" : -1,
   "objs" : [
      {
         "when_comp_start" : 1,
         "url" : "http://modified.testbed.localhost/www.kidsfoni.com/",
         "id" : "r1",
         "comps" : [
            {
               "s_time" : 49.6100001037121,
               "time" : -3361855512.298,
               "id" : "r1_c1",
               "type" : "evalhtml",
               "e_time" : -3361855462.688
            },
            {
               "s_time" : 113.729000091553,
               "time" : -3361855576.417,
               "id" : "r1_c2",
               "type" : "evalhtml",
               "e_time" : -3361855462.688
            },
            {
               "s_time" : 114.281999878585,
               "time" : 1.38900009915301,
               "id" : "r1_c3",
               "type" : "evalhtml",
               "e_time" : 115.670999977738
            },
            {
               "s_time" : 118.402999825776,
               "time" : -3361855581.091,
               "id" : "r1_c4",
               "type" : "evalhtml",
               "e_time" : -3361855462.688
            },
            {
               "s_time" : 119.820000138134,
               "time" : -3361855582.508,
               "id" : "r1_c5",
               "type" : "evalhtml",
               "e_time" : -3361855462.688
            },
            {
               "s_time" : 122.499000281096,
               "time" : -3361855585.187,
               "id" : "r1_c6",
               "type" : "evalhtml",
               "e_time" : -3361855462.688
            },
            {
               "s_time" : 123.070000205189,
               "time" : -3361855585.758,
               "id" : "r1_c7",
               "type" : "evalhtml",
               "e_time" : -3361855462.688
            },
            {
               "s_time" : 124.71600016579,
               "time" : -3361855587.404,
               "id" : "r1_c8",
               "type" : "evalhtml",
               "e_time" : -3361855462.688
            },
            {
               "s_time" : 125.642000231892,
               "time" : 373.385000042617,
               "id" : "r1_c9",
               "type" : "evalhtml",
               "e_time" : 499.027000274509
            },
            {
               "s_time" : 504.866000264883,
               "time" : -3361855967.554,
               "id" : "r1_c10",
               "type" : "evalhtml",
               "e_time" : -3361855462.688
            },
            {
               "s_time" : 505.764999892563,
               "time" : -3361855968.453,
               "id" : "r1_c11",
               "type" : "evalhtml",
               "e_time" : -3361855462.688
            },
            {
               "s_time" : 506.238000001758,
               "time" : -3361855968.926,
               "id" : "r1_c12",
               "type" : "evalhtml",
               "e_time" : -3361855462.688
            },
            {
               "s_time" : 506.822000257671,
               "time" : -3361855969.51,
               "id" : "r1_c13",
               "type" : "evalhtml",
               "e_time" : -3361855462.688
            },
            {
               "s_time" : 507.127000018954,
               "time" : -3361855969.815,
               "id" : "r1_c14",
               "type" : "evalhtml",
               "e_time" : -3361855462.688
            },
            {
               "s_time" : 507.2579998523,
               "time" : 34.293000120669,
               "id" : "r1_c15",
               "type" : "evalhtml",
               "e_time" : 541.550999972969
            },
            {
               "s_time" : 572.598000057042,
               "time" : -3361856035.286,
               "id" : "r1_c16",
               "type" : "evalhtml",
               "e_time" : -3361855462.688
            },
            {
               "s_time" : 572.995000053197,
               "time" : -3361856035.683,
               "id" : "r1_c17",
               "type" : "evalhtml",
               "e_time" : -3361855462.688
            },
            {
               "s_time" : 575.246000196785,
               "time" : -3361856037.934,
               "id" : "r1_c18",
               "type" : "evalhtml",
               "e_time" : -3361855462.688
            },
            {
               "s_time" : 575.594000052661,
               "time" : -3361856038.282,
               "id" : "r1_c19",
               "type" : "evalhtml",
               "e_time" : -3361855462.688
            },
            {
               "s_time" : 575.899000279605,
               "time" : 783.859999850395,
               "id" : "r1_c20",
               "type" : "evalhtml",
               "e_time" : 1359.75900013
            },
            {
               "s_time" : 1924.57000026479,
               "time" : -3361857387.258,
               "id" : "r1_c21",
               "type" : "evalhtml",
               "e_time" : -3361855462.688
            },
            {
               "s_time" : 1924.7850002721,
               "time" : -3361857387.473,
               "id" : "r1_c22",
               "type" : "evalhtml",
               "e_time" : -3361855462.688
            },
            {
               "s_time" : 1924.9749998562,
               "time" : -3361857387.663,
               "id" : "r1_c23",
               "type" : "evalhtml",
               "e_time" : -3361855462.688
            },
            {
               "s_time" : 1925.14599999413,
               "time" : 0.0470001250498626,
               "type" : "evalhtml",
               "id" : "r1_c24",
               "e_time" : 1925.19300011918
            }
         ],
         "download" : {
            "receiveFirst" : 4,
            "len" : 139819,
            "dns" : 0,
            "dnsEnd" : -1,
            "receiveHeadersEnd" : 5,
            "sslEnd" : -1,
            "connectEnd" : 1,
            "connectStart" : 0,
            "id" : "download_0",
            "receivedTime" : "48.9400001242757",
            "sslStart" : -1,
            "dnsStart" : -1,
            "receiveLast" : 43.9400001242757,
            "s_time" : 0,
            "sendEnd" : 1,
            "sendStart" : 1,
            "type" : "text/html"
         }
      },
      {
         "when_comp_start" : 1,
         "url" : "http://modified.testbed.localhost/Themes/Kidsfoni_New_350/Content/images/logo.png",
         "id" : "r30",
         "comps" : [],
         "download" : {
            "receiveFirst" : 9,
            "len" : 337,
            "dns" : 0,
            "dnsEnd" : -1,
            "receiveHeadersEnd" : 14,
            "sslEnd" : -1,
            "connectEnd" : 5,
            "connectStart" : 0,
            "id" : "download_1",
            "receivedTime" : "206.881999969482",
            "sslStart" : -1,
            "dnsStart" : -1,
            "receiveLast" : 192.881999969482,
            "s_time" : 115.670999977738,
            "sendEnd" : 5,
            "sendStart" : 5,
            "type" : "text/html"
         }
      },
      {
         "when_comp_start" : -1,
         "url" : "http://kidsfoni.com/content/images/thumbs/0065298.png",
         "id" : "r31",
         "comps" : [],
         "download" : {
            "receiveFirst" : 3,
            "len" : 631281,
            "dns" : 0,
            "dnsEnd" : -1,
            "receiveHeadersEnd" : 3,
            "sslEnd" : -1,
            "connectEnd" : 0,
            "connectStart" : 0,
            "id" : "download_2",
            "receivedTime" : "494.615000206977",
            "sslStart" : -1,
            "dnsStart" : -1,
            "receiveLast" : 491.615000206977,
            "s_time" : 126.8380000256,
            "sendEnd" : 0,
            "sendStart" : 0,
            "type" : "image/png"
         }
      },
      {
         "when_comp_start" : -1,
         "url" : "http://kidsfoni.com/content/images/thumbs/0065220.jpeg",
         "id" : "r32",
         "comps" : [],
         "download" : {
            "receiveFirst" : 3,
            "len" : 44363,
            "dns" : 0,
            "dnsEnd" : -1,
            "receiveHeadersEnd" : 3,
            "sslEnd" : -1,
            "connectEnd" : 0,
            "connectStart" : 0,
            "id" : "download_3",
            "receivedTime" : "213.886000216007",
            "sslStart" : -1,
            "dnsStart" : -1,
            "receiveLast" : 210.886000216007,
            "s_time" : 127.286999952048,
            "sendEnd" : 0,
            "sendStart" : 0,
            "type" : "image/jpeg"
         }
      },
      {
         "when_comp_start" : -1,
         "url" : "http://kidsfoni.com/content/images/thumbs/0065255.png",
         "id" : "r33",
         "comps" : [],
         "download" : {
            "receiveFirst" : 3,
            "len" : 412119,
            "dns" : 0,
            "dnsEnd" : -1,
            "receiveHeadersEnd" : 3,
            "sslEnd" : -1,
            "connectEnd" : 0,
            "connectStart" : 0,
            "id" : "download_4",
            "receivedTime" : "218.392000067979",
            "sslStart" : -1,
            "dnsStart" : -1,
            "receiveLast" : 215.392000067979,
            "s_time" : 127.724000252783,
            "sendEnd" : 0,
            "sendStart" : 0,
            "type" : "image/png"
         }
      },
      {
         "when_comp_start" : -1,
         "url" : "http://kidsfoni.com/content/images/thumbs/0064978.png",
         "id" : "r34",
         "comps" : [],
         "download" : {
            "receiveFirst" : 3,
            "len" : 1238881,
            "dns" : 0,
            "dnsEnd" : -1,
            "receiveHeadersEnd" : 3,
            "sslEnd" : -1,
            "connectEnd" : 0,
            "connectStart" : 0,
            "id" : "download_5",
            "receivedTime" : "576.055999845266",
            "sslStart" : -1,
            "dnsStart" : -1,
            "receiveLast" : 573.055999845266,
            "s_time" : 128.295999951661,
            "sendEnd" : 0,
            "sendStart" : 0,
            "type" : "image/png"
         }
      },
      {
         "when_comp_start" : -1,
         "url" : "https://assets.zendesk.com/embeddable_framework/main.js",
         "id" : "r35",
         "comps" : [
            {
               "s_time" : 580.73200006038,
               "time" : 435.88199978694,
               "type" : 2,
               "id" : "comp_130",
               "e_time" : 1016.61399984732
            },
            {
               "s_time" : 1419.4060000591,
               "time" : 262.79400009662,
               "type" : null,
               "id" : "comp_157",
               "e_time" : 1682.20000015572
            }
         ],
         "download" : {
            "receiveFirst" : 7,
            "len" : 888053,
            "dns" : 0,
            "dnsEnd" : -1,
            "receiveHeadersEnd" : 7,
            "sslEnd" : -1,
            "connectEnd" : 0,
            "connectStart" : 0,
            "id" : "download_6",
            "receivedTime" : "571.736000012606",
            "sslStart" : -1,
            "dnsStart" : -1,
            "receiveLast" : 564.736000012606,
            "s_time" : 149.755999911577,
            "sendEnd" : 0,
            "sendStart" : 0,
            "type" : "application/javascript"
         }
      },
      {
         "when_comp_start" : -1,
         "url" : "http://connect.facebook.net/tr_TR/sdk.js#xfbml=1&version=v2.4&appId=1642719142676378",
         "id" : "r36",
         "comps" : [],
         "download" : {
            "receiveFirst" : 8,
            "len" : 186153,
            "dns" : 0,
            "dnsEnd" : -1,
            "receiveHeadersEnd" : 8,
            "sslEnd" : -1,
            "connectEnd" : 0,
            "connectStart" : 0,
            "id" : "download_7",
            "receivedTime" : "237.654999829829",
            "sslStart" : -1,
            "dnsStart" : -1,
            "receiveLast" : 229.654999829829,
            "s_time" : 154.263000003994,
            "sendEnd" : 0,
            "sendStart" : 0,
            "type" : "application/x-javascript"
         }
      },
      {
         "when_comp_start" : -1,
         "url" : "http://kidsfoni.com/content/images/thumbs/0065141_dunyanin-1-numarali-cocuk-cumhuriyeti-kidzaniaya-cocuk-giris-bileti-80-tl-yerine-49-tl_304.png",
         "id" : "r37",
         "comps" : [],
         "download" : {
            "receiveFirst" : 7,
            "len" : 151861,
            "dns" : 0,
            "dnsEnd" : -1,
            "receiveHeadersEnd" : 7,
            "sslEnd" : -1,
            "connectEnd" : 0,
            "connectStart" : 0,
            "id" : "download_8",
            "receivedTime" : "236.260000150651",
            "sslStart" : -1,
            "dnsStart" : -1,
            "receiveLast" : 229.260000150651,
            "s_time" : 158.356999978423,
            "sendEnd" : 0,
            "sendStart" : 0,
            "type" : "image/png"
         }
      },
      {
         "when_comp_start" : -1,
         "url" : "http://kidsfoni.com/content/images/thumbs/0065305_amerikanin-yaz-kampi-atasehirdecocuklar-icin-full-ngilizce_304.jpeg",
         "id" : "r38",
         "comps" : [],
         "download" : {
            "receiveFirst" : 7,
            "len" : 19284,
            "dns" : 0,
            "dnsEnd" : -1,
            "receiveHeadersEnd" : 7,
            "sslEnd" : -1,
            "connectEnd" : 0,
            "connectStart" : 0,
            "id" : "download_9",
            "receivedTime" : "229.468999896199",
            "sslStart" : -1,
            "dnsStart" : -1,
            "receiveLast" : 222.468999896199,
            "s_time" : 158.840999938548,
            "sendEnd" : 0,
            "sendStart" : 0,
            "type" : "image/jpeg"
         }
      },
      {
         "when_comp_start" : -1,
         "url" : "http://kidsfoni.com/content/images/thumbs/0065252_ates-bizi-cagiriyor-ozel-kamp-kampanyasi_304.png",
         "id" : "r39",
         "comps" : [],
         "download" : {
            "receiveFirst" : 7,
            "len" : 117915,
            "dns" : 0,
            "dnsEnd" : -1,
            "receiveHeadersEnd" : 7,
            "sslEnd" : -1,
            "connectEnd" : 0,
            "connectStart" : 0,
            "id" : "download_10",
            "receivedTime" : "234.722999855876",
            "sslStart" : -1,
            "dnsStart" : -1,
            "receiveLast" : 227.722999855876,
            "s_time" : 159.249000251293,
            "sendEnd" : 0,
            "sendStart" : 0,
            "type" : "image/png"
         }
      },
      {
         "when_comp_start" : -1,
         "url" : "http://kidsfoni.com/content/images/thumbs/0065259_viasea-tema-parkta-gunluk-sinirsiz-giris-49-tl_304.png",
         "id" : "r40",
         "comps" : [],
         "download" : {
            "receiveFirst" : 8,
            "len" : 144597,
            "dns" : 0,
            "dnsEnd" : -1,
            "receiveHeadersEnd" : 8,
            "sslEnd" : -1,
            "connectEnd" : 0,
            "connectStart" : 0,
            "id" : "download_11",
            "receivedTime" : "236.688000150025",
            "sslStart" : -1,
            "dnsStart" : -1,
            "receiveLast" : 228.688000150025,
            "s_time" : 159.663999918848,
            "sendEnd" : 0,
            "sendStart" : 0,
            "type" : "image/png"
         }
      },
      {
         "when_comp_start" : -1,
         "url" : "http://kidsfoni.com/content/images/thumbs/0065304_kidsfonide-lk-kez-gunluk-bakim-hizmeti_304.jpeg",
         "id" : "r41",
         "comps" : [],
         "download" : {
            "receiveFirst" : 7,
            "len" : 17491,
            "dns" : 0,
            "dnsEnd" : -1,
            "receiveHeadersEnd" : 7,
            "sslEnd" : -1,
            "connectEnd" : 0,
            "connectStart" : 0,
            "id" : "download_12",
            "receivedTime" : "230.314000044018",
            "sslStart" : -1,
            "dnsStart" : -1,
            "receiveLast" : 223.314000044018,
            "s_time" : 160.079000052065,
            "sendEnd" : 0,
            "sendStart" : 0,
            "type" : "image/jpeg"
         }
      },
      {
         "when_comp_start" : -1,
         "url" : "http://kidsfoni.com/content/images/thumbs/0065106_sealife-akvaryum-biletleri-31-tl-yerine-1850-tl_304.png",
         "id" : "r42",
         "comps" : [],
         "download" : {
            "receiveFirst" : 7,
            "len" : 155710,
            "dns" : 0,
            "dnsEnd" : -1,
            "receiveHeadersEnd" : 7,
            "sslEnd" : -1,
            "connectEnd" : 0,
            "connectStart" : 0,
            "id" : "download_13",
            "receivedTime" : "236.945000011474",
            "sslStart" : -1,
            "dnsStart" : -1,
            "receiveLast" : 229.945000011474,
            "s_time" : 160.504000261426,
            "sendEnd" : 0,
            "sendStart" : 0,
            "type" : "image/png"
         }
      },
      {
         "when_comp_start" : -1,
         "url" : "http://kidsfoni.com/content/images/thumbs/0064977_turkiyenin-lk-cocuk-sehri-kidzmondoya-giris-bileti-60-tl-yerine-45-tl_304.png",
         "id" : "r43",
         "comps" : [],
         "download" : {
            "receiveFirst" : 7,
            "len" : 147015,
            "dns" : 0,
            "dnsEnd" : -1,
            "receiveHeadersEnd" : 7,
            "sslEnd" : -1,
            "connectEnd" : 0,
            "connectStart" : 0,
            "id" : "download_14",
            "receivedTime" : "237.236000131816",
            "sslStart" : -1,
            "dnsStart" : -1,
            "receiveLast" : 230.236000131816,
            "s_time" : 160.966999828815,
            "sendEnd" : 0,
            "sendStart" : 0,
            "type" : "image/png"
         }
      },
      {
         "when_comp_start" : -1,
         "url" : "http://kidsfoni.com/content/images/thumbs/0065221_vialand-dogum-gunu-paketleri-ile-tum-gun-sinirsiz-eglence_304.png",
         "id" : "r44",
         "comps" : [],
         "download" : {
            "receiveFirst" : 7,
            "len" : 122874,
            "dns" : 0,
            "dnsEnd" : -1,
            "receiveHeadersEnd" : 7,
            "sslEnd" : -1,
            "connectEnd" : 0,
            "connectStart" : 0,
            "id" : "download_15",
            "receivedTime" : "235.743000172079",
            "sslStart" : -1,
            "dnsStart" : -1,
            "receiveLast" : 228.743000172079,
            "s_time" : 161.429999861866,
            "sendEnd" : 0,
            "sendStart" : 0,
            "type" : "image/png"
         }
      },
      {
         "when_comp_start" : -1,
         "url" : "http://kidsfoni.com/content/images/thumbs/0065182_xtrem-aventuresin-bahara-ozel-kampanyasi-ile-20-tlden-baslayan-fiyatlar_304.png",
         "id" : "r45",
         "comps" : [],
         "download" : {
            "receiveFirst" : 5,
            "len" : 157184,
            "dns" : 0,
            "dnsEnd" : -1,
            "receiveHeadersEnd" : 5,
            "sslEnd" : -1,
            "connectEnd" : 0,
            "connectStart" : 0,
            "id" : "download_16",
            "receivedTime" : "325.935000088066",
            "sslStart" : -1,
            "dnsStart" : -1,
            "receiveLast" : 320.935000088066,
            "s_time" : 172.104999888688,
            "sendEnd" : 0,
            "sendStart" : 0,
            "type" : "image/png"
         }
      },
      {
         "when_comp_start" : -1,
         "url" : "http://kidsfoni.com/content/images/thumbs/0065058_stanbul-kelebek-ciftliginde-kelebeklerle-tanisma-20-tlden-baslayan-fiyatlarla_304.jpeg",
         "id" : "r46",
         "comps" : [],
         "download" : {
            "receiveFirst" : 7,
            "len" : 14873,
            "dns" : 0,
            "dnsEnd" : -1,
            "receiveHeadersEnd" : 7,
            "sslEnd" : -1,
            "connectEnd" : 0,
            "connectStart" : 0,
            "id" : "download_17",
            "receivedTime" : "235.158000141382",
            "sslStart" : -1,
            "dnsStart" : -1,
            "receiveLast" : 228.158000141382,
            "s_time" : 173.464000225067,
            "sendEnd" : 0,
            "sendStart" : 0,
            "type" : "image/jpeg"
         }
      },
      {
         "when_comp_start" : -1,
         "url" : "http://kidsfoni.com/content/images/thumbs/0065286_the-zone-maslakta-cocuklar-icin-hem-eglenceli-hem-egitici-aktiviteler-30-tlden-baslayan-fiyatlarla_304.png",
         "id" : "r47",
         "comps" : [],
         "download" : {
            "receiveFirst" : 4,
            "len" : 93767,
            "dns" : 0,
            "dnsEnd" : -1,
            "receiveHeadersEnd" : 4,
            "sslEnd" : -1,
            "connectEnd" : 0,
            "connectStart" : 0,
            "id" : "download_18",
            "receivedTime" : "490.548000205308",
            "sslStart" : -1,
            "dnsStart" : -1,
            "receiveLast" : 486.548000205308,
            "s_time" : 184.330999851227,
            "sendEnd" : 0,
            "sendStart" : 0,
            "type" : "image/png"
         }
      },
      {
         "when_comp_start" : -1,
         "url" : "http://kidsfoni.com/content/images/thumbs/0065225_halat-by-divandan-ailece-pazar-keyfi-acik-bufe-kahvalti-sonrasi-muze-gezisi-paketi-32-tlden-baslayan_304.png",
         "id" : "r48",
         "comps" : [],
         "download" : {
            "receiveFirst" : 4,
            "len" : 152904,
            "dns" : 0,
            "dnsEnd" : -1,
            "receiveHeadersEnd" : 4,
            "sslEnd" : -1,
            "connectEnd" : 0,
            "connectStart" : 0,
            "id" : "download_19",
            "receivedTime" : "492.769999895245",
            "sslStart" : -1,
            "dnsStart" : -1,
            "receiveLast" : 488.769999895245,
            "s_time" : 184.532999992371,
            "sendEnd" : 0,
            "sendStart" : 0,
            "type" : "image/png"
         }
      },
      {
         "when_comp_start" : -1,
         "url" : "http://kidsfoni.com/content/images/thumbs/0063979_funloft-oyun-makinelerinden-30-tllik-oyun-karti-alana-30-tl-hediye_304.png",
         "id" : "r49",
         "comps" : [],
         "download" : {
            "receiveFirst" : 4,
            "len" : 153416,
            "dns" : 0,
            "dnsEnd" : -1,
            "receiveHeadersEnd" : 4,
            "sslEnd" : -1,
            "connectEnd" : 0,
            "connectStart" : 0,
            "id" : "download_20",
            "receivedTime" : "493.815999943763",
            "sslStart" : -1,
            "dnsStart" : -1,
            "receiveLast" : 489.815999943763,
            "s_time" : 185.47199992463,
            "sendEnd" : 0,
            "sendStart" : 0,
            "type" : "image/png"
         }
      },
      {
         "when_comp_start" : -1,
         "url" : "http://kidsfoni.com/content/images/thumbs/0064981_funloftta-30-dk-playground-girisi-12-tl-15-dk-ucretsiz-giris-hakki-hediye_304.jpeg",
         "id" : "r50",
         "comps" : [],
         "download" : {
            "receiveFirst" : 12,
            "len" : 23717,
            "dns" : 0,
            "dnsEnd" : -1,
            "receiveHeadersEnd" : 12,
            "sslEnd" : -1,
            "connectEnd" : 0,
            "connectStart" : 0,
            "id" : "download_21",
            "receivedTime" : "493.280000053346",
            "sslStart" : -1,
            "dnsStart" : -1,
            "receiveLast" : 481.280000053346,
            "s_time" : 192.896999884397,
            "sendEnd" : 0,
            "sendStart" : 0,
            "type" : "image/jpeg"
         }
      },
      {
         "when_comp_start" : -1,
         "url" : "http://kidsfoni.com/content/images/thumbs/0065186_kozyatagi-med-akademiden-alaninda-uzman-egitmenler-esliginde-cocuklar-ve-yetiskinler-icin-lk-yardim-_304.png",
         "id" : "r51",
         "comps" : [],
         "download" : {
            "receiveFirst" : 13,
            "len" : 117955,
            "dns" : 0,
            "dnsEnd" : -1,
            "receiveHeadersEnd" : 13,
            "sslEnd" : -1,
            "connectEnd" : 0,
            "connectStart" : 0,
            "id" : "download_22",
            "receivedTime" : "503.062000032514",
            "sslStart" : -1,
            "dnsStart" : -1,
            "receiveLast" : 490.062000032514,
            "s_time" : 193.406000267714,
            "sendEnd" : 0,
            "sendStart" : 0,
            "type" : "image/png"
         }
      },
      {
         "when_comp_start" : -1,
         "url" : "http://kidsfoni.com/content/images/thumbs/0065192_sutisten-baby-shower-ve-1-3-yas-dogum-gunu-paketleri-sadece-cengelkoy-subesi-icin-gecerlidir_304.png",
         "id" : "r52",
         "comps" : [],
         "download" : {
            "receiveFirst" : 12,
            "len" : 169122,
            "dns" : 0,
            "dnsEnd" : -1,
            "receiveHeadersEnd" : 12,
            "sslEnd" : -1,
            "connectEnd" : 0,
            "connectStart" : 0,
            "id" : "download_23",
            "receivedTime" : "509.579000063241",
            "sslStart" : -1,
            "dnsStart" : -1,
            "receiveLast" : 497.579000063241,
            "s_time" : 193.849999923259,
            "sendEnd" : 0,
            "sendStart" : 0,
            "type" : "image/png"
         }
      },
      {
         "when_comp_start" : -1,
         "url" : "http://kidsfoni.com/content/images/thumbs/0064974_su-sagliktir-swimbabyde-bebekler-icin-su-aktivitesi-deneme-dersi-130-tl-yerine-118-tl_304.jpeg",
         "id" : "r53",
         "comps" : [],
         "download" : {
            "receiveFirst" : 11,
            "len" : 19528,
            "dns" : 0,
            "dnsEnd" : -1,
            "receiveHeadersEnd" : 11,
            "sslEnd" : -1,
            "connectEnd" : 0,
            "connectStart" : 0,
            "id" : "download_24",
            "receivedTime" : "499.228999949992",
            "sslStart" : -1,
            "dnsStart" : -1,
            "receiveLast" : 488.228999949992,
            "s_time" : 195.019000209868,
            "sendEnd" : 0,
            "sendStart" : 0,
            "type" : "image/jpeg"
         }
      },
      {
         "when_comp_start" : -1,
         "url" : "http://kidsfoni.com/content/images/thumbs/0064965_bubblevents-parti-evinde-dogum-gunu-partisi-1500-tl-yerine-1100-tl_304.jpeg",
         "id" : "r54",
         "comps" : [],
         "download" : {
            "receiveFirst" : 9,
            "len" : 22023,
            "dns" : 0,
            "dnsEnd" : -1,
            "receiveHeadersEnd" : 10,
            "sslEnd" : -1,
            "connectEnd" : 1,
            "connectStart" : 0,
            "id" : "download_25",
            "receivedTime" : "499.571000225842",
            "sslStart" : -1,
            "dnsStart" : -1,
            "receiveLast" : 489.571000225842,
            "s_time" : 195.567999966443,
            "sendEnd" : 1,
            "sendStart" : 1,
            "type" : "image/jpeg"
         }
      },
      {
         "when_comp_start" : -1,
         "url" : "http://kidsfoni.com/content/images/thumbs/0064987_okay-temiz-ritim-atolyesi-ebeveyncocuk-aylik-toplam-4ders-ritim-kursu-290-tl-yerine-225-tl_304.jpeg",
         "id" : "r55",
         "comps" : [],
         "download" : {
            "receiveFirst" : 6,
            "len" : 17244,
            "dns" : 0,
            "dnsEnd" : -1,
            "receiveHeadersEnd" : 6,
            "sslEnd" : -1,
            "connectEnd" : 0,
            "connectStart" : 0,
            "id" : "download_26",
            "receivedTime" : "499.888000078499",
            "sslStart" : -1,
            "dnsStart" : -1,
            "receiveLast" : 493.888000078499,
            "s_time" : 199.60100017488,
            "sendEnd" : 0,
            "sendStart" : 0,
            "type" : "image/jpeg"
         }
      },
      {
         "when_comp_start" : -1,
         "url" : "http://kidsfoni.com/content/images/thumbs/0064317_kovan-spor-kulturunde-12-derslik-jimnastik-paketi-300-tl_304.jpeg",
         "id" : "r56",
         "comps" : [],
         "download" : {
            "receiveFirst" : 14,
            "len" : 13005,
            "dns" : 0,
            "dnsEnd" : -1,
            "receiveHeadersEnd" : 92,
            "sslEnd" : -1,
            "connectEnd" : 78,
            "connectStart" : 0,
            "id" : "download_27",
            "receivedTime" : "501.141000073403",
            "sslStart" : -1,
            "dnsStart" : -1,
            "receiveLast" : 409.141000073403,
            "s_time" : 206.532999873161,
            "sendEnd" : 78,
            "sendStart" : 78,
            "type" : "image/jpeg"
         }
      },
      {
         "when_comp_start" : -1,
         "url" : "http://kidsfoni.com/content/images/thumbs/0064315_zeynep-gulden-sonsuza-kadar-saklanacak-dogum-ve-dogum-gunu-fotograflari-750-tl-yerine-500-tl_304.png",
         "id" : "r57",
         "comps" : [],
         "download" : {
            "receiveFirst" : 14,
            "len" : 90373,
            "dns" : 0,
            "dnsEnd" : -1,
            "receiveHeadersEnd" : 92,
            "sslEnd" : -1,
            "connectEnd" : 78,
            "connectStart" : 0,
            "id" : "download_28",
            "receivedTime" : "505.282999947667",
            "sslStart" : -1,
            "dnsStart" : -1,
            "receiveLast" : 413.282999947667,
            "s_time" : 207.106000278145,
            "sendEnd" : 78,
            "sendStart" : 78,
            "type" : "image/png"
         }
      },
      {
         "when_comp_start" : -1,
         "url" : "http://kidsfoni.com/content/images/thumbs/0063988_stanbul-kids-clubdan-ngilizce-yuzme-jimnastik-kurslarinda-4-ders-120tlden-baslayan-indirimli-fiyatla_304.png",
         "id" : "r58",
         "comps" : [],
         "download" : {
            "receiveFirst" : 14,
            "len" : 153913,
            "dns" : 0,
            "dnsEnd" : -1,
            "receiveHeadersEnd" : 92,
            "sslEnd" : -1,
            "connectEnd" : 78,
            "connectStart" : 0,
            "id" : "download_29",
            "receivedTime" : "510.993000119925",
            "sslStart" : -1,
            "dnsStart" : -1,
            "receiveLast" : 418.993000119925,
            "s_time" : 207.783000078052,
            "sendEnd" : 78,
            "sendStart" : 78,
            "type" : "image/png"
         }
      },
      {
         "when_comp_start" : -1,
         "url" : "http://kidsfoni.com/content/images/thumbs/0064985_minikler-icin-12-derslik-satranc-kursu-kovan-spor-kulturunde-300-tl-tek-derslik-fiyati-80-tl_304.jpeg",
         "id" : "r59",
         "comps" : [],
         "download" : {
            "receiveFirst" : 14,
            "len" : 19776,
            "dns" : 0,
            "dnsEnd" : -1,
            "receiveHeadersEnd" : 85,
            "sslEnd" : -1,
            "connectEnd" : 71,
            "connectStart" : 0,
            "id" : "download_30",
            "receivedTime" : "502.106000203639",
            "sslStart" : -1,
            "dnsStart" : -1,
            "receiveLast" : 417.106000203639,
            "s_time" : 214.841000270098,
            "sendEnd" : 71,
            "sendStart" : 71,
            "type" : "image/jpeg"
         }
      },
      {
         "when_comp_start" : -1,
         "url" : "http://kidsfoni.com/content/images/thumbs/0064309_nar-party-evinde-dogum-gunu-partisi-1250-tl-yerine-1150-tlden-baslayan-fiyatlarla_304.png",
         "id" : "r60",
         "comps" : [],
         "download" : {
            "receiveFirst" : 11,
            "len" : 148141,
            "dns" : 0,
            "dnsEnd" : -1,
            "receiveHeadersEnd" : 11,
            "sslEnd" : -1,
            "connectEnd" : 0,
            "connectStart" : 0,
            "id" : "download_31",
            "receivedTime" : "523.23399996385",
            "sslStart" : -1,
            "dnsStart" : -1,
            "receiveLast" : 512.23399996385,
            "s_time" : 296.200000215322,
            "sendEnd" : 0,
            "sendStart" : 0,
            "type" : "image/png"
         }
      },
      {
         "when_comp_start" : -1,
         "url" : "http://kidsfoni.com/content/images/thumbs/0064546_atasehir-asia-city-hotelde-tatli-surprizler-10-16-yas-karaoke-etkinligi-kisi-basi-118-tl-hamburger-m_304.jpeg",
         "id" : "r61",
         "comps" : [],
         "download" : {
            "receiveFirst" : 10,
            "len" : 12346,
            "dns" : 0,
            "dnsEnd" : -1,
            "receiveHeadersEnd" : 10,
            "sslEnd" : -1,
            "connectEnd" : 0,
            "connectStart" : 0,
            "id" : "download_32",
            "receivedTime" : "504.043000284582",
            "sslStart" : -1,
            "dnsStart" : -1,
            "receiveLast" : 494.043000284582,
            "s_time" : 298.160000238568,
            "sendEnd" : 0,
            "sendStart" : 0,
            "type" : "image/jpeg"
         }
      },
      {
         "when_comp_start" : -1,
         "url" : "http://kidsfoni.com/content/images/thumbs/0064979_atolye-fulden-cocuklar-icin-cikolata-yapimi-atolyesi-100-tl-yerine-39-tl_304.jpeg",
         "id" : "r62",
         "comps" : [],
         "download" : {
            "receiveFirst" : 10,
            "len" : 21980,
            "dns" : 0,
            "dnsEnd" : -1,
            "receiveHeadersEnd" : 10,
            "sslEnd" : -1,
            "connectEnd" : 0,
            "connectStart" : 0,
            "id" : "download_33",
            "receivedTime" : "504.360999912024",
            "sslStart" : -1,
            "dnsStart" : -1,
            "receiveLast" : 494.360999912024,
            "s_time" : 298.955000005662,
            "sendEnd" : 0,
            "sendStart" : 0,
            "type" : "image/jpeg"
         }
      },
      {
         "when_comp_start" : -1,
         "url" : "http://kidsfoni.com/content/images/thumbs/0063782_stanbul-kumpanyasi-2015-2016-sezonu-cocuk-ve-yetiskin-oyunlarina-kombine-giris-biletleri-225-tl-yeri_304.jpeg",
         "id" : "r63",
         "comps" : [],
         "download" : {
            "receiveFirst" : 8,
            "len" : 17032,
            "dns" : 0,
            "dnsEnd" : -1,
            "receiveHeadersEnd" : 8,
            "sslEnd" : -1,
            "connectEnd" : 0,
            "connectStart" : 0,
            "id" : "download_34",
            "receivedTime" : "508.400999940932",
            "sslStart" : -1,
            "dnsStart" : -1,
            "receiveLast" : 500.400999940932,
            "s_time" : 305.819999892265,
            "sendEnd" : 0,
            "sendStart" : 0,
            "type" : "image/jpeg"
         }
      },
      {
         "when_comp_start" : -1,
         "url" : "http://kidsfoni.com/content/images/thumbs/0065095_son-dakika-dogum-gunu-partileri-bubblevents-parti-evinde-sadece-900-tl_304.jpeg",
         "id" : "r64",
         "comps" : [],
         "download" : {
            "receiveFirst" : 10,
            "len" : 26295,
            "dns" : 0,
            "dnsEnd" : -1,
            "receiveHeadersEnd" : 10,
            "sslEnd" : -1,
            "connectEnd" : 0,
            "connectStart" : 0,
            "id" : "download_35",
            "receivedTime" : "509.053000248969",
            "sslStart" : -1,
            "dnsStart" : -1,
            "receiveLast" : 499.053000248969,
            "s_time" : 307.980000041425,
            "sendEnd" : 0,
            "sendStart" : 0,
            "type" : "image/jpeg"
         }
      },
      {
         "when_comp_start" : -1,
         "url" : "http://kidsfoni.com/content/images/thumbs/0064970_darussafaka-norse-spor-tesisleri-fethi-oztoprak-yuzme-okulu-ozel-ve-grup-dersleri-80-tlden-baslayan-_304.jpeg",
         "id" : "r65",
         "comps" : [],
         "download" : {
            "receiveFirst" : 9,
            "len" : 25346,
            "dns" : 0,
            "dnsEnd" : -1,
            "receiveHeadersEnd" : 9,
            "sslEnd" : -1,
            "connectEnd" : 0,
            "connectStart" : 0,
            "id" : "download_36",
            "receivedTime" : "509.858000092208",
            "sslStart" : -1,
            "dnsStart" : -1,
            "receiveLast" : 500.858000092208,
            "s_time" : 309.634999837726,
            "sendEnd" : 0,
            "sendStart" : 0,
            "type" : "image/jpeg"
         }
      },
      {
         "when_comp_start" : -1,
         "url" : "http://kidsfoni.com/content/images/thumbs/0064946_hibricker-ile-cocugunuzla-beraber-istediginiz-binayi-yapabilirsiniz-ustelik-8990-tlden-baslayan-fiya_304.jpeg",
         "id" : "r66",
         "comps" : [],
         "download" : {
            "receiveFirst" : 7,
            "len" : 11312,
            "dns" : 0,
            "dnsEnd" : -1,
            "receiveHeadersEnd" : 7,
            "sslEnd" : -1,
            "connectEnd" : 0,
            "connectStart" : 0,
            "id" : "download_37",
            "receivedTime" : "510.219000279903",
            "sslStart" : -1,
            "dnsStart" : -1,
            "receiveLast" : 503.219000279903,
            "s_time" : 311.546000186354,
            "sendEnd" : 0,
            "sendStart" : 0,
            "type" : "image/jpeg"
         }
      },
      {
         "when_comp_start" : -1,
         "url" : "http://kidsfoni.com/content/images/thumbs/0064947_magic-nuudles-activity-hayal-gucu-bloklari-2490-yerine-1990-tlden-baslayan-fiyatlarla_304.jpeg",
         "id" : "r67",
         "comps" : [],
         "download" : {
            "receiveFirst" : 7,
            "len" : 10276,
            "dns" : 0,
            "dnsEnd" : -1,
            "receiveHeadersEnd" : 7,
            "sslEnd" : -1,
            "connectEnd" : 0,
            "connectStart" : 0,
            "id" : "download_38",
            "receivedTime" : "510.737000033259",
            "sslStart" : -1,
            "dnsStart" : -1,
            "receiveLast" : 503.737000033259,
            "s_time" : 312.475000042468,
            "sendEnd" : 0,
            "sendStart" : 0,
            "type" : "image/jpeg"
         }
      },
      {
         "when_comp_start" : -1,
         "url" : "http://kidsfoni.com/content/images/thumbs/0065069_aslan-ile-fare-kurnaz-tilkiye-karsi-cocuk-oyunu-23-nisan-2016-cumartesi-saat-1500de-torium-avmde-25-_304.png",
         "id" : "r68",
         "comps" : [],
         "download" : {
            "receiveFirst" : 13,
            "len" : 202233,
            "dns" : 0,
            "dnsEnd" : -1,
            "receiveHeadersEnd" : 13,
            "sslEnd" : -1,
            "connectEnd" : 0,
            "connectStart" : 0,
            "id" : "download_39",
            "receivedTime" : "526.984000112861",
            "sslStart" : -1,
            "dnsStart" : -1,
            "receiveLast" : 513.984000112861,
            "s_time" : 315.565000288188,
            "sendEnd" : 0,
            "sendStart" : 0,
            "type" : "image/png"
         }
      },
      {
         "when_comp_start" : -1,
         "url" : "http://kidsfoni.com/content/images/thumbs/0065096_nar-party-evinden-eglenceli-oyunlarla-dolu-baby-shower-partisi-1450-tl-yerine-1300-tl_304.jpeg",
         "id" : "r69",
         "comps" : [],
         "download" : {
            "receiveFirst" : 14,
            "len" : 13412,
            "dns" : 0,
            "dnsEnd" : -1,
            "receiveHeadersEnd" : 14,
            "sslEnd" : -1,
            "connectEnd" : 0,
            "connectStart" : 0,
            "id" : "download_40",
            "receivedTime" : "524.050999898463",
            "sslStart" : -1,
            "dnsStart" : -1,
            "receiveLast" : 510.050999898463,
            "s_time" : 321.433000266552,
            "sendEnd" : 0,
            "sendStart" : 0,
            "type" : "image/jpeg"
         }
      },
      {
         "when_comp_start" : -1,
         "url" : "http://kidsfoni.com/content/images/thumbs/0064964_jenny-jimmy-kids-social-clubta-0-7-yas-arasi-cocuklara-ozel-1-aylik-aktiviteler-350-tl-yerine-sadece_304.jpeg",
         "id" : "r70",
         "comps" : [],
         "download" : {
            "receiveFirst" : 11,
            "len" : 14811,
            "dns" : 0,
            "dnsEnd" : -1,
            "receiveHeadersEnd" : 11,
            "sslEnd" : -1,
            "connectEnd" : 0,
            "connectStart" : 0,
            "id" : "download_41",
            "receivedTime" : "524.41000007093",
            "sslStart" : -1,
            "dnsStart" : -1,
            "receiveLast" : 513.41000007093,
            "s_time" : 325.436000246555,
            "sendEnd" : 0,
            "sendStart" : 0,
            "type" : "image/jpeg"
         }
      },
      {
         "when_comp_start" : -1,
         "url" : "http://kidsfoni.com/content/images/thumbs/0064976_gymboree-playlearn-muzik-ve-sanat-derslerinde-12-ders-1200-tlden-baslayan-fiyatlarla-ustelik-2-ders-_304.jpeg",
         "id" : "r71",
         "comps" : [],
         "download" : {
            "receiveFirst" : 11,
            "len" : 25811,
            "dns" : 0,
            "dnsEnd" : -1,
            "receiveHeadersEnd" : 11,
            "sslEnd" : -1,
            "connectEnd" : 0,
            "connectStart" : 0,
            "id" : "download_42",
            "receivedTime" : "524.718999862671",
            "sslStart" : -1,
            "dnsStart" : -1,
            "receiveLast" : 513.718999862671,
            "s_time" : 326.720000244677,
            "sendEnd" : 0,
            "sendStart" : 0,
            "type" : "image/jpeg"
         }
      },
      {
         "when_comp_start" : -1,
         "url" : "http://kidsfoni.com/content/images/thumbs/0064915_kovan-spor-kulturunde-tenis-ile-guclu-saglikli-ve-mutlu-cocuklar-10-derslik-paket-300-tl_304.jpeg",
         "id" : "r72",
         "comps" : [],
         "download" : {
            "receiveFirst" : 10,
            "len" : 12445,
            "dns" : 0,
            "dnsEnd" : -1,
            "receiveHeadersEnd" : 10,
            "sslEnd" : -1,
            "connectEnd" : 0,
            "connectStart" : 0,
            "id" : "download_43",
            "receivedTime" : "525.061000138521",
            "sslStart" : -1,
            "dnsStart" : -1,
            "receiveLast" : 515.061000138521,
            "s_time" : 327.653000131249,
            "sendEnd" : 0,
            "sendStart" : 0,
            "type" : "image/jpeg"
         }
      },
      {
         "when_comp_start" : 1,
         "url" : "http://modified.testbed.localhost/Themes/Kidsfoni_New_350/Content/images/jenny_jimmy_mailing_14.11.05.jpg",
         "id" : "r73",
         "comps" : [],
         "download" : {
            "receiveFirst" : 9,
            "len" : 361,
            "dns" : 0,
            "dnsEnd" : -1,
            "receiveHeadersEnd" : 16,
            "sslEnd" : -1,
            "connectEnd" : 6,
            "connectStart" : 0,
            "id" : "download_44",
            "receivedTime" : "526.181000284851",
            "sslStart" : -1,
            "dnsStart" : -1,
            "receiveLast" : 510.181000284851,
            "s_time" : 328.577000182122,
            "sendEnd" : 7,
            "sendStart" : 6,
            "type" : "text/html"
         }
      },
      {
         "when_comp_start" : 1,
         "url" : "http://modified.testbed.localhost/Themes/Kidsfoni_New_350/Content/images/bannerKids.jpg",
         "id" : "r74",
         "comps" : [],
         "download" : {
            "receiveFirst" : 8,
            "len" : 343,
            "dns" : 0,
            "dnsEnd" : -1,
            "receiveHeadersEnd" : 16,
            "sslEnd" : -1,
            "connectEnd" : 8,
            "connectStart" : 0,
            "id" : "download_45",
            "receivedTime" : "526.351000182331",
            "sslStart" : -1,
            "dnsStart" : -1,
            "receiveLast" : 510.351000182331,
            "s_time" : 329.989999998361,
            "sendEnd" : 8,
            "sendStart" : 8,
            "type" : "text/html"
         }
      },
      {
         "when_comp_start" : 1,
         "url" : "http://modified.testbed.localhost/Themes/Kidsfoni_New_350/Content/images/campaign.png",
         "id" : "r75",
         "comps" : [],
         "download" : {
            "receiveFirst" : 7,
            "len" : 341,
            "dns" : 0,
            "dnsEnd" : -1,
            "receiveHeadersEnd" : 15,
            "sslEnd" : -1,
            "connectEnd" : 7,
            "connectStart" : 0,
            "id" : "download_46",
            "receivedTime" : "526.698000263423",
            "sslStart" : -1,
            "dnsStart" : -1,
            "receiveLast" : 511.698000263423,
            "s_time" : 330.920999869704,
            "sendEnd" : 8,
            "sendStart" : 7,
            "type" : "text/html"
         }
      },
      {
         "when_comp_start" : 1,
         "url" : "http://modified.testbed.localhost/Themes/Kidsfoni_New_350/Content/images/footer-add.png",
         "id" : "r76",
         "comps" : [],
         "download" : {
            "receiveFirst" : 5,
            "len" : 343,
            "dns" : 0,
            "dnsEnd" : -1,
            "receiveHeadersEnd" : 12,
            "sslEnd" : -1,
            "connectEnd" : 7,
            "connectStart" : 0,
            "id" : "download_47",
            "receivedTime" : "527.637999970466",
            "sslStart" : -1,
            "dnsStart" : -1,
            "receiveLast" : 515.637999970466,
            "s_time" : 337.05099998042,
            "sendEnd" : 7,
            "sendStart" : 7,
            "type" : "text/html"
         }
      },
      {
         "when_comp_start" : 1,
         "url" : "http://modified.testbed.localhost/Themes/Kidsfoni_New_350/Content/images/visa-payment.png",
         "id" : "r77",
         "comps" : [],
         "download" : {
            "receiveFirst" : 6,
            "len" : 345,
            "dns" : 0,
            "dnsEnd" : -1,
            "receiveHeadersEnd" : 11,
            "sslEnd" : -1,
            "connectEnd" : 5,
            "connectStart" : 0,
            "id" : "download_48",
            "receivedTime" : "527.825000230223",
            "sslStart" : -1,
            "dnsStart" : -1,
            "receiveLast" : 516.825000230223,
            "s_time" : 339.230000041425,
            "sendEnd" : 5,
            "sendStart" : 5,
            "type" : "text/html"
         }
      },
      {
         "when_comp_start" : 1,
         "url" : "http://modified.testbed.localhost/Themes/Kidsfoni_New_350/Content/images/master-card-payment.png",
         "id" : "r78",
         "comps" : [],
         "download" : {
            "receiveFirst" : 6,
            "len" : 352,
            "dns" : 0,
            "dnsEnd" : -1,
            "receiveHeadersEnd" : 10,
            "sslEnd" : -1,
            "connectEnd" : 4,
            "connectStart" : 0,
            "id" : "download_49",
            "receivedTime" : "528.034000191838",
            "sslStart" : -1,
            "dnsStart" : -1,
            "receiveLast" : 518.034000191838,
            "s_time" : 340.776999946684,
            "sendEnd" : 4,
            "sendStart" : 4,
            "type" : "text/html"
         }
      },
      {
         "when_comp_start" : 1,
         "url" : "http://modified.testbed.localhost/Themes/Kidsfoni_New_350/Content/images/rapaid-payment.png",
         "id" : "r79",
         "comps" : [],
         "download" : {
            "receiveFirst" : 4,
            "len" : 347,
            "dns" : 0,
            "dnsEnd" : -1,
            "receiveHeadersEnd" : 11,
            "sslEnd" : -1,
            "connectEnd" : 6,
            "connectStart" : 0,
            "id" : "download_50",
            "receivedTime" : "528.506999835372",
            "sslStart" : -1,
            "dnsStart" : -1,
            "receiveLast" : 517.506999835372,
            "s_time" : 341.998000163585,
            "sendEnd" : 7,
            "sendStart" : 6,
            "type" : "text/html"
         }
      },
      {
         "when_comp_start" : 1,
         "url" : "http://modified.testbed.localhost/Themes/Kidsfoni_New_350/Content/images/img/kids/imalathanelogo.png",
         "id" : "r80",
         "comps" : [],
         "download" : {
            "receiveFirst" : 4,
            "len" : 356,
            "dns" : 0,
            "dnsEnd" : -1,
            "receiveHeadersEnd" : 10,
            "sslEnd" : -1,
            "connectEnd" : 6,
            "connectStart" : 0,
            "id" : "download_51",
            "receivedTime" : "528.687000274658",
            "sslStart" : -1,
            "dnsStart" : -1,
            "receiveLast" : 518.687000274658,
            "s_time" : 343.034000135958,
            "sendEnd" : 6,
            "sendStart" : 6,
            "type" : "text/html"
         }
      },
      {
         "when_comp_start" : -1,
         "url" : "https://www.google-analytics.com/analytics.js",
         "id" : "r81",
         "comps" : [],
         "download" : {
            "receiveFirst" : 6,
            "len" : 26299,
            "dns" : 0,
            "dnsEnd" : -1,
            "receiveHeadersEnd" : 6,
            "sslEnd" : -1,
            "connectEnd" : 0,
            "connectStart" : 0,
            "id" : "download_52",
            "receivedTime" : "574.727000202984",
            "sslStart" : -1,
            "dnsStart" : -1,
            "receiveLast" : 568.727000202984,
            "s_time" : 499.027000274509,
            "sendEnd" : 0,
            "sendStart" : 0,
            "type" : "text/javascript"
         }
      },
      {
         "when_comp_start" : 1,
         "url" : "http://staticxx.facebook.com/connect/xd_arbiter.php?version=42#channel=fe0ff753&origin=http%3A%2F%2Fmodified.testbed.localhost",
         "id" : "r99",
         "comps" : [
            {
               "s_time" : 1151.49000007659,
               "time" : 26.26499999315,
               "type" : "evalhtml",
               "id" : "r99_c1",
               "e_time" : 1177.75500006974
            }
         ],
         "download" : {
            "receiveFirst" : 3,
            "len" : 34898,
            "dns" : 0,
            "dnsEnd" : -1,
            "receiveHeadersEnd" : 3,
            "sslEnd" : -1,
            "connectEnd" : 0,
            "connectStart" : 0,
            "id" : "download_53",
            "receivedTime" : "1040.06400005892",
            "sslStart" : -1,
            "dnsStart" : -1,
            "receiveLast" : 1037.06400005892,
            "s_time" : 583.738999906927,
            "sendEnd" : 0,
            "sendStart" : 0,
            "type" : "text/html"
         }
      },
      {
         "when_comp_start" : 1,
         "url" : "https://staticxx.facebook.com/connect/xd_arbiter.php?version=42#channel=fe0ff753&origin=http%3A%2F%2Fmodified.testbed.localhost",
         "id" : "r100",
         "comps" : [
            {
               "s_time" : 1151.90399996936,
               "time" : 49.0100001916301,
               "type" : "evalhtml",
               "id" : "r100_c1",
               "e_time" : 1200.91400016099
            }
         ],
         "download" : {
            "receiveFirst" : 3,
            "len" : 34898,
            "dns" : 0,
            "dnsEnd" : -1,
            "receiveHeadersEnd" : 3,
            "sslEnd" : -1,
            "connectEnd" : 0,
            "connectStart" : 0,
            "id" : "download_54",
            "receivedTime" : "1040.45800026506",
            "sslStart" : -1,
            "dnsStart" : -1,
            "receiveLast" : 1037.45800026506,
            "s_time" : 584.367000032216,
            "sendEnd" : 0,
            "sendStart" : 0,
            "type" : "text/html"
         }
      },
      {
         "when_comp_start" : -1,
         "url" : "https://www.facebook.com/impression.php/f48e597a4/?api_key=1642719142676378&lid=115&payload=%7B%22source%22%3A%22jssdk%22%7D",
         "id" : "r93",
         "comps" : [],
         "download" : {
            "receiveFirst" : 54,
            "len" : 43,
            "dns" : 0,
            "dnsEnd" : 1,
            "receiveHeadersEnd" : 105,
            "sslEnd" : 48,
            "connectEnd" : 50,
            "connectStart" : 0,
            "id" : "download_55",
            "receivedTime" : "1041.53400007635",
            "sslStart" : 14,
            "dnsStart" : 1,
            "receiveLast" : 936.534000076354,
            "s_time" : 541.550999972969,
            "sendEnd" : 51,
            "sendStart" : 50,
            "type" : "image/gif"
         }
      },
      {
         "when_comp_start" : -1,
         "url" : "https://www.google-analytics.com/collect?v=1&_v=j41&a=800664531&t=pageview&_s=1&dl=http%3A%2F%2Fmodified.testbed.localhost%2Fwww.kidsfoni.com%2F&ul=en-us&de=UTF-8&sd=24-bit&sr=1024x768&vp=989x599&je=1&_utma=10762024.337840052.1461875325.1461875325.1461875325.1&_utmz=10762024.1461875325.1.1.utmcsr%3D",
         "id" : "r101",
         "comps" : [],
         "download" : {
            "receiveFirst" : 7,
            "len" : 35,
            "dns" : 0,
            "dnsEnd" : 1,
            "receiveHeadersEnd" : 44,
            "sslEnd" : 25,
            "connectEnd" : 26,
            "connectStart" : 0,
            "id" : "download_56",
            "receivedTime" : "1404.18400010094",
            "sslStart" : 7,
            "dnsStart" : 1,
            "receiveLast" : 1360.18400010094,
            "s_time" : 1355.03700003028,
            "sendEnd" : 37,
            "sendStart" : 26,
            "type" : "image/gif"
         }
      },
      {
         "when_comp_start" : 1,
         "url" : "https://assets.zendesk.com/embeddable_framework/update.html?1461879129245#b365bfe",
         "id" : "r102",
         "comps" : [
            {
               "s_time" : 1418.14400022849,
               "time" : 0.938999932260003,
               "type" : "evalhtml",
               "id" : "r102_c1",
               "e_time" : 1419.08300016075
            }
         ],
         "download" : {
            "receiveFirst" : 15,
            "len" : 268,
            "dns" : 0,
            "dnsEnd" : 0,
            "receiveHeadersEnd" : 46,
            "sslEnd" : 29,
            "connectEnd" : 29,
            "connectStart" : 0,
            "id" : "download_57",
            "receivedTime" : "1407.91099984199",
            "sslStart" : 5,
            "dnsStart" : 0,
            "receiveLast" : 1361.91099984199,
            "s_time" : 1359.75900013,
            "sendEnd" : 31,
            "sendStart" : 29,
            "type" : "text/html"
         }
      }
   ],
   "deps" : [
      {
         "a2" : "r1_c2",
         "time" : -1,
         "id" : "dep1",
         "a1" : "comp_20"
      },
      {
         "a2" : "r1_c3",
         "time" : -1,
         "id" : "dep2",
         "a1" : "comp_21"
      },
      {
         "a2" : "r1_c4",
         "time" : -1,
         "id" : "dep3",
         "a1" : "comp_22"
      },
      {
         "a2" : "r1_c5",
         "time" : -1,
         "id" : "dep4",
         "a1" : "comp_23"
      },
      {
         "a2" : "r1_c6",
         "time" : -1,
         "id" : "dep5",
         "a1" : "comp_24"
      },
      {
         "a2" : "r1_c7",
         "time" : -1,
         "id" : "dep6",
         "a1" : "comp_25"
      },
      {
         "a2" : "r1_c8",
         "time" : -1,
         "id" : "dep7",
         "a1" : "comp_26"
      },
      {
         "a2" : "r1_c9",
         "time" : -1,
         "id" : "dep8",
         "a1" : "comp_27"
      },
      {
         "a2" : "r1_c10",
         "time" : -1,
         "id" : "dep9",
         "a1" : "comp_52"
      },
      {
         "a2" : "r1_c11",
         "time" : -1,
         "id" : "dep10",
         "a1" : "comp_53"
      },
      {
         "a2" : "r1_c12",
         "time" : -1,
         "id" : "dep11",
         "a1" : "comp_54"
      },
      {
         "a2" : "r1_c13",
         "time" : -1,
         "id" : "dep12",
         "a1" : "comp_55"
      },
      {
         "a2" : "r1_c14",
         "time" : -1,
         "id" : "dep13",
         "a1" : "comp_56"
      },
      {
         "a2" : "r1_c15",
         "time" : -1,
         "id" : "dep14",
         "a1" : "comp_57"
      },
      {
         "a2" : "r1_c16",
         "time" : -1,
         "id" : "dep15",
         "a1" : "comp_125"
      },
      {
         "a2" : "r1_c17",
         "time" : -1,
         "id" : "dep16",
         "a1" : "comp_126"
      },
      {
         "a2" : "r1_c18",
         "time" : -1,
         "id" : "dep17",
         "a1" : "comp_127"
      },
      {
         "a2" : "r1_c19",
         "time" : -1,
         "id" : "dep18",
         "a1" : "comp_128"
      },
      {
         "a2" : "r1_c20",
         "time" : -1,
         "id" : "dep19",
         "a1" : "comp_129"
      },
      {
         "a2" : "r1_c21",
         "time" : -1,
         "id" : "dep20",
         "a1" : "comp_167"
      },
      {
         "a2" : "r1_c22",
         "time" : -1,
         "id" : "dep21",
         "a1" : "comp_168"
      },
      {
         "a2" : "r1_c23",
         "time" : -1,
         "id" : "dep22",
         "a1" : "comp_169"
      },
      {
         "a2" : "r1_c24",
         "time" : -1,
         "id" : "dep23",
         "a1" : "comp_170"
      },
      {
         "a2" : "download_57",
         "time" : -1,
         "id" : "dep24",
         "a1" : "r1_c20"
      },
      {
         "a2" : "download_56",
         "time" : 779.137999750675,
         "id" : "dep25",
         "a1" : "r1_c20"
      },
      {
         "a2" : "download_55",
         "time" : -1,
         "id" : "dep26",
         "a1" : "r1_c15"
      },
      {
         "a2" : "download_54",
         "time" : 8.46799975261092,
         "id" : "dep27",
         "a1" : "r1_c20"
      },
      {
         "a2" : "download_53",
         "time" : 7.83999962732196,
         "id" : "dep28",
         "a1" : "r1_c20"
      },
      {
         "a2" : "download_52",
         "time" : -1,
         "id" : "dep29",
         "a1" : "r1_c9"
      },
      {
         "a2" : "download_51",
         "time" : 217.391999904066,
         "id" : "dep30",
         "a1" : "r1_c9"
      },
      {
         "a2" : "download_50",
         "time" : 216.355999931693,
         "id" : "dep31",
         "a1" : "r1_c9"
      },
      {
         "a2" : "download_49",
         "time" : 215.134999714792,
         "id" : "dep32",
         "a1" : "r1_c9"
      },
      {
         "a2" : "download_48",
         "time" : 213.587999809533,
         "id" : "dep33",
         "a1" : "r1_c9"
      },
      {
         "a2" : "download_47",
         "time" : 211.408999748528,
         "id" : "dep34",
         "a1" : "r1_c9"
      },
      {
         "a2" : "download_46",
         "time" : 205.278999637812,
         "id" : "dep35",
         "a1" : "r1_c9"
      },
      {
         "a2" : "download_45",
         "time" : 204.347999766469,
         "id" : "dep36",
         "a1" : "r1_c9"
      },
      {
         "a2" : "download_44",
         "time" : 202.93499995023,
         "id" : "dep37",
         "a1" : "r1_c9"
      },
      {
         "a2" : "download_43",
         "time" : 202.010999899357,
         "id" : "dep38",
         "a1" : "r1_c9"
      },
      {
         "a2" : "download_42",
         "time" : 201.078000012785,
         "id" : "dep39",
         "a1" : "r1_c9"
      },
      {
         "a2" : "download_41",
         "time" : 199.794000014663,
         "id" : "dep40",
         "a1" : "r1_c9"
      },
      {
         "a2" : "download_40",
         "time" : 195.79100003466,
         "id" : "dep41",
         "a1" : "r1_c9"
      },
      {
         "a2" : "download_39",
         "time" : 189.923000056296,
         "id" : "dep42",
         "a1" : "r1_c9"
      },
      {
         "a2" : "download_38",
         "time" : 186.832999810576,
         "id" : "dep43",
         "a1" : "r1_c9"
      },
      {
         "a2" : "download_37",
         "time" : 185.903999954462,
         "id" : "dep44",
         "a1" : "r1_c9"
      },
      {
         "a2" : "download_36",
         "time" : 183.992999605834,
         "id" : "dep45",
         "a1" : "r1_c9"
      },
      {
         "a2" : "download_35",
         "time" : 182.337999809533,
         "id" : "dep46",
         "a1" : "r1_c9"
      },
      {
         "a2" : "download_34",
         "time" : 180.177999660373,
         "id" : "dep47",
         "a1" : "r1_c9"
      },
      {
         "a2" : "download_33",
         "time" : 173.31299977377,
         "id" : "dep48",
         "a1" : "r1_c9"
      },
      {
         "a2" : "download_32",
         "time" : 172.518000006676,
         "id" : "dep49",
         "a1" : "r1_c9"
      },
      {
         "a2" : "download_31",
         "time" : 170.55799998343,
         "id" : "dep50",
         "a1" : "r1_c9"
      },
      {
         "a2" : "download_30",
         "time" : 89.199000038206,
         "id" : "dep51",
         "a1" : "r1_c9"
      },
      {
         "a2" : "download_29",
         "time" : 82.14099984616,
         "id" : "dep52",
         "a1" : "r1_c9"
      },
      {
         "a2" : "download_28",
         "time" : 81.464000046253,
         "id" : "dep53",
         "a1" : "r1_c9"
      },
      {
         "a2" : "download_27",
         "time" : 80.890999641269,
         "id" : "dep54",
         "a1" : "r1_c9"
      },
      {
         "a2" : "download_26",
         "time" : 73.958999942988,
         "id" : "dep55",
         "a1" : "r1_c9"
      },
      {
         "a2" : "download_25",
         "time" : 69.925999734551,
         "id" : "dep56",
         "a1" : "r1_c9"
      },
      {
         "a2" : "download_24",
         "time" : 69.376999977976,
         "id" : "dep57",
         "a1" : "r1_c9"
      },
      {
         "a2" : "download_23",
         "time" : 68.207999691367,
         "id" : "dep58",
         "a1" : "r1_c9"
      },
      {
         "a2" : "download_22",
         "time" : 67.764000035822,
         "id" : "dep59",
         "a1" : "r1_c9"
      },
      {
         "a2" : "download_21",
         "time" : 67.254999652505,
         "id" : "dep60",
         "a1" : "r1_c9"
      },
      {
         "a2" : "download_20",
         "time" : 59.829999692738,
         "id" : "dep61",
         "a1" : "r1_c9"
      },
      {
         "a2" : "download_19",
         "time" : 58.890999760479,
         "id" : "dep62",
         "a1" : "r1_c9"
      },
      {
         "a2" : "download_18",
         "time" : 58.688999619335,
         "id" : "dep63",
         "a1" : "r1_c9"
      },
      {
         "a2" : "download_17",
         "time" : 47.821999993175,
         "id" : "dep64",
         "a1" : "r1_c9"
      },
      {
         "a2" : "download_16",
         "time" : 46.462999656796,
         "id" : "dep65",
         "a1" : "r1_c9"
      },
      {
         "a2" : "download_15",
         "time" : 35.787999629974,
         "id" : "dep66",
         "a1" : "r1_c9"
      },
      {
         "a2" : "download_14",
         "time" : 35.324999596923,
         "id" : "dep67",
         "a1" : "r1_c9"
      },
      {
         "a2" : "download_13",
         "time" : 34.862000029534,
         "id" : "dep68",
         "a1" : "r1_c9"
      },
      {
         "a2" : "download_12",
         "time" : 34.436999820173,
         "id" : "dep69",
         "a1" : "r1_c9"
      },
      {
         "a2" : "download_11",
         "time" : 34.021999686956,
         "id" : "dep70",
         "a1" : "r1_c9"
      },
      {
         "a2" : "download_10",
         "time" : 33.607000019401,
         "id" : "dep71",
         "a1" : "r1_c9"
      },
      {
         "a2" : "download_9",
         "time" : 33.198999706656,
         "id" : "dep72",
         "a1" : "r1_c9"
      },
      {
         "a2" : "download_8",
         "time" : 32.714999746531,
         "id" : "dep73",
         "a1" : "r1_c9"
      },
      {
         "a2" : "download_7",
         "time" : 28.620999772102,
         "id" : "dep74",
         "a1" : "r1_c9"
      },
      {
         "a2" : "download_6",
         "time" : 24.113999679685,
         "id" : "dep75",
         "a1" : "r1_c9"
      },
      {
         "a2" : "download_5",
         "time" : 2.653999719769,
         "id" : "dep76",
         "a1" : "r1_c9"
      },
      {
         "a2" : "download_4",
         "time" : 2.082000020891,
         "id" : "dep77",
         "a1" : "r1_c9"
      },
      {
         "a2" : "download_3",
         "time" : 1.64499972015601,
         "id" : "dep78",
         "a1" : "r1_c9"
      },
      {
         "a2" : "download_2",
         "time" : 1.195999793708,
         "id" : "dep79",
         "a1" : "r1_c9"
      },
      {
         "a2" : "download_1",
         "time" : -1,
         "id" : "dep80",
         "a1" : "r1_c3"
      },
      {
         "a2" : "download_1",
         "time" : 1.38900009915301,
         "id" : "dep81",
         "a1" : "r1_c3"
      }
   ]
}
