{
   "n_download_no_trigger" : 1,
   "start_activity" : "download_0",
   "name" : "modified.testbed.localhost_www.latimes.com",
   "load_activity" : -1,
   "objs" : [
      {
         "when_comp_start" : 1,
         "url" : "http://modified.testbed.localhost/www.latimes.com",
         "id" : "r1",
         "comps" : [
            {
               "s_time" : 99.0079999901354,
               "time" : 0.502000097185402,
               "type" : "evalhtml",
               "id" : "r1_c1",
               "e_time" : 99.5100000873208
            }
         ],
         "download" : {
            "receiveFirst" : 45,
            "len" : 381,
            "dns" : 0,
            "dnsEnd" : -1,
            "receiveHeadersEnd" : 61,
            "sslEnd" : -1,
            "connectEnd" : 15,
            "connectStart" : 0,
            "id" : "download_0",
            "receivedTime" : "63.0569998174906",
            "sslStart" : -1,
            "dnsStart" : -1,
            "receiveLast" : 2.05699981749058,
            "s_time" : 0,
            "sendEnd" : 16,
            "sendStart" : 15,
            "type" : "text/html"
         }
      }
   ],
   "deps" : []
}
